airiam/Reporter.py
airiam/__init__.py
airiam/banner.py
airiam/main.py
airiam/version.py
airiam/find_unused/PolicyAnalyzer.py
airiam/find_unused/RuntimeIamScanner.py
airiam/find_unused/__init__.py
airiam/find_unused/find_unused.py
airiam/models/RuntimeReport.py
airiam/models/__init__.py
airiam/recommend_groups/__init__.py
airiam/recommend_groups/recommend_groups.py
airiam/terraform/TerraformTransformer.py
airiam/terraform/__init__.py
airiam/terraform/entity_terraformers/AWSProviderTransformer.py
airiam/terraform/entity_terraformers/BaseEntityTransformer.py
airiam/terraform/entity_terraformers/IAMGroupMembershipsTransformer.py
airiam/terraform/entity_terraformers/IAMGroupTransformer.py
airiam/terraform/entity_terraformers/IAMInlinePolicyTransformer.py
airiam/terraform/entity_terraformers/IAMManagedPolicyAttachmentTransformer.py
airiam/terraform/entity_terraformers/IAMPolicyDocumentTransformer.py
airiam/terraform/entity_terraformers/IAMPolicyTransformer.py
airiam/terraform/entity_terraformers/IAMRoleTransformer.py
airiam/terraform/entity_terraformers/IAMUserGroupMembershipTransformer.py
airiam/terraform/entity_terraformers/IAMUserTransformer.py
airiam/terraform/entity_terraformers/InstancProfileTransformer.py
airiam/terraform/entity_terraformers/__init__.py
airiam-0.1.83.data/scripts/airiam
airiam-0.1.83.data/scripts/airiam.cmd
airiam-0.1.83.dist-info/LICENSE
airiam-0.1.83.dist-info/METADATA
airiam-0.1.83.dist-info/WHEEL
airiam-0.1.83.dist-info/top_level.txt
airiam-0.1.83.dist-info/RECORD
