Metadata-Version: 2.1
Name: airiam
Version: 0.1.83
Summary: Least privilege AWS IAM Terraformer
Home-page: https://github.com/bridgecrewio/AirIAM
Author: bridgecrew
Author-email: meet@bridgecrew.io
License: Apache License 2.0
Classifier: Environment :: Console
Classifier: Intended Audience :: Developers
Classifier: Intended Audience :: System Administrators
Classifier: Programming Language :: Python :: 3.7
Classifier: Topic :: Security
Classifier: Topic :: Software Development :: Build Tools
License-File: LICENSE
Requires-Dist: boto3 (>=1.12.43)
Requires-Dist: colorama (==0.4.3)
Requires-Dist: python-terraform (==0.10.1)
Requires-Dist: requests (>=2.22.0)
Requires-Dist: termcolor (==1.1.0)
Provides-Extra: dev
Requires-Dist: Cerberus (==1.3.2) ; extra == 'dev'
Requires-Dist: coverage (==5.0.4) ; extra == 'dev'
Requires-Dist: coverage-badge (==1.0.1) ; extra == 'dev'
Requires-Dist: moto (==1.3.14) ; extra == 'dev'
Requires-Dist: pipenv-setup (==3.0.1) ; extra == 'dev'
Requires-Dist: pytest (==5.4.1) ; extra == 'dev'
